[
  {
    "question": "insert",
    "answer": "삽입하다",
    "memo": "Insert a coin."
  },
  {
    "question": "ethic (ethical)",
    "answer": "윤리 (윤리적인)",
    "memo": "Work ethic."
  },
  {
    "question": "headquarters",
    "answer": "본부",
    "memo": "The company's headquarters."
  },
  {
    "question": "interfere",
    "answer": "간섭하다",
    "memo": "Don't interfere."
  },
  {
    "question": "riot",
    "answer": "폭동",
    "memo": "A street riot."
  },
  {
    "question": "inherent",
    "answer": "내재된, 타고난",
    "memo": "Inherent danger."
  },
  {
    "question": "absolute",
    "answer": "절대적인, 완전한",
    "memo": "You must keep it an absolute secret."
  },
  {
    "question": "biography",
    "answer": "전기(일대기)",
    "memo": "I'm reading a biography of Lincoln."
  },
  {
    "question": "hook",
    "answer": "갈고리, 걸다",
    "memo": "Hang it on the hook."
  },
  {
    "question": "collaborate",
    "answer": "협력하다",
    "memo": "We collaborated on the project."
  },
  {
    "question": "imply",
    "answer": "암시하다",
    "memo": "What do you imply?"
  },
  {
    "question": "confront",
    "answer": "직면하다",
    "memo": "Confront the problem."
  },
  {
    "question": "blend",
    "answer": "섞다, 혼합물",
    "memo": "Blend the fruit and yogurt."
  },
  {
    "question": "compile",
    "answer": "편집하다, 수집하다",
    "memo": "Compile a dictionary."
  },
  {
    "question": "mechanic",
    "answer": "정비공",
    "memo": "A car mechanic."
  },
  {
    "question": "discriminate",
    "answer": "차별하다, 구별하다",
    "memo": "Discriminate against minorities."
  },
  {
    "question": "roar",
    "answer": "으르렁거리다, 함성",
    "memo": "A lion's roar."
  },
  {
    "question": "resume",
    "answer": "다시 시작하다, 이력서",
    "memo": "Send a resume."
  },
  {
    "question": "motive",
    "answer": "동기",
    "memo": "The motive for the crime."
  },
  {
    "question": "superior",
    "answer": "우월한, 상급의",
    "memo": "Superior quality."
  },
  {
    "question": "rumor / rumour",
    "answer": "소문",
    "memo": "Spread a rumor."
  },
  {
    "question": "accumulate",
    "answer": "축적하다, 모으다",
    "memo": "Snow began to accumulate on the road."
  },
  {
    "question": "prevail",
    "answer": "우세하다, 널리 퍼지다",
    "memo": "Justice will prevail."
  },
  {
    "question": "descend",
    "answer": "내려가다",
    "memo": "Descend the stairs."
  },
  {
    "question": "publish (publisher)",
    "answer": "출판하다 (출판사)",
    "memo": "Publish a book."
  },
  {
    "question": "rage",
    "answer": "분노, 격노",
    "memo": "Road rage."
  },
  {
    "question": "refrigerate (refrigerator)",
    "answer": "냉장하다 (냉장고)",
    "memo": "Put it in the refrigerator."
  },
  {
    "question": "manifest",
    "answer": "명백한, 나타내다",
    "memo": "His anger was manifest."
  },
  {
    "question": "ideology",
    "answer": "이데올로기",
    "memo": "Political ideology."
  },
  {
    "question": "extraordinary",
    "answer": "놀라운, 비범한",
    "memo": "An extraordinary talent."
  },
  {
    "question": "yield",
    "answer": "산출하다, 양보하다",
    "memo": "Yield to traffic."
  },
  {
    "question": "await",
    "answer": "기다리다",
    "memo": "A surprise awaits you."
  },
  {
    "question": "surrender",
    "answer": "굴복하다, 항복",
    "memo": "Surrender to the enemy."
  },
  {
    "question": "leisure",
    "answer": "여가",
    "memo": "Leisure time."
  },
  {
    "question": "aspire",
    "answer": "열망하다",
    "memo": "He aspires to be a great writer."
  },
  {
    "question": "resort",
    "answer": "휴양지, 의지하다",
    "memo": "A summer resort."
  },
  {
    "question": "reinforce",
    "answer": "강화하다",
    "memo": "Reinforce the wall."
  },
  {
    "question": "intelligent",
    "answer": "똑똑한",
    "memo": "Intelligent robots."
  },
  {
    "question": "mock",
    "answer": "조롱하다, 가짜의",
    "memo": "Mock exam."
  },
  {
    "question": "geology",
    "answer": "지질학",
    "memo": "Study geology."
  },
  {
    "question": "colony",
    "answer": "식민지, 집단",
    "memo": "An ant colony."
  },
  {
    "question": "gamble",
    "answer": "도박하다",
    "memo": "Don't gamble with your life."
  },
  {
    "question": "weed",
    "answer": "잡초",
    "memo": "Pull out weeds."
  },
  {
    "question": "analyze / analyse",
    "answer": "분석하다",
    "memo": "We need to analyze the data."
  },
  {
    "question": "welfare",
    "answer": "복지",
    "memo": "Social welfare."
  },
  {
    "question": "spectacle",
    "answer": "광경, 안경",
    "memo": "A grand spectacle."
  },
  {
    "question": "scatter",
    "answer": "흩뿌리다",
    "memo": "Scatter seeds."
  },
  {
    "question": "flush",
    "answer": "물에 씻어 내리다, 홍조",
    "memo": "Flush the toilet."
  },
  {
    "question": "rural",
    "answer": "시골의",
    "memo": "Rural areas."
  },
  {
    "question": "mineral",
    "answer": "미네랄, 광물",
    "memo": "Mineral water."
  }
]